{
  "featured": {
    "name": "super slime bros",
    "image": "https://raw.githubusercontent.com/RoturTW/apps/refs/heads/main/all/super%20slime%20bros/screenshots/Screenshot%202024-08-21%20at%2020.22.16.png",
    "desc": "A simple local multiplayer brawler!!!",
    "auth": "Mist"
  },
  "tiles": [
    {"title": "originkill"},
    {"title": "oft"},
    {"title": "fluficord"},
    {"title": "fortnite skibidi 2024"},
    {"title": "origincord"},
    {"title": "originfy"},
    {"title": "arrow"},
    {"title": "claw"}
  ]
}
